ocdc/__init__.py
ocdc/__main__.py
ocdc/api.py
ocdc/ast.py
ocdc/parser.py
ocdc/renderer.py
ocdc-0.5.0.dist-info/LICENSE
ocdc-0.5.0.dist-info/METADATA
ocdc-0.5.0.dist-info/WHEEL
ocdc-0.5.0.dist-info/entry_points.txt
ocdc-0.5.0.dist-info/RECORD
