Metadata-Version: 2.1
Name: ocdc
Version: 0.5.0
Summary: A changelog formatter for "people", neat freaks, and sloppy typists.
Home-page: https://github.com/mdwint/ocdc
License: MIT
Keywords: changelog,markdown,formatter
Author: Matteo De Wint
Author-email: matteo@mailfence.com
Requires-Python: >=3.8,<4.0
Classifier: License :: OSI Approved :: MIT License
Classifier: Programming Language :: Python :: 3
Classifier: Programming Language :: Python :: 3.8
Classifier: Programming Language :: Python :: 3.9
Classifier: Programming Language :: Python :: 3.10
Classifier: Programming Language :: Python :: 3.11
Requires-Dist: packaging (>=23.1,<24.0)
Requires-Dist: pydantic (>=2.0.2,<3.0.0)
Project-URL: Repository, https://github.com/mdwint/ocdc
